linearcorex/__init__.py
linearcorex/linearcorex.py
linearcorex-0.53.dist-info/LICENSE
linearcorex-0.53.dist-info/METADATA
linearcorex-0.53.dist-info/WHEEL
linearcorex-0.53.dist-info/top_level.txt
linearcorex-0.53.dist-info/RECORD
