Metadata-Version: 2.1
Name: linearcorex
Version: 0.53
Summary: Linear CorEx finds latent factors that explain relationships in data.
Home-page: https://github.com/gregversteeg/linearcorex
Author: Greg Ver Steeg
Author-email: gversteeg@gmail.com
License: UNKNOWN
Platform: UNKNOWN
Classifier: Programming Language :: Python :: 3
Classifier: Operating System :: OS Independent
